scraperapi_mcp_server/__init__.py
scraperapi_mcp_server/__main__.py
scraperapi_mcp_server/config.py
scraperapi_mcp_server/scrape/models.py
scraperapi_mcp_server/scrape/scrape.py
scraperapi_mcp_server/server.py
scraperapi_mcp_server/utils/country_codes.py
scraperapi_mcp_server/utils/exceptions.py
scraperapi_mcp_server-0.1.1.dist-info/METADATA
scraperapi_mcp_server-0.1.1.dist-info/WHEEL
scraperapi_mcp_server-0.1.1.dist-info/entry_points.txt
scraperapi_mcp_server-0.1.1.dist-info/RECORD
