Metadata-Version: 2.3
Name: scraperapi-mcp-server
Version: 0.1.1
Summary: ScraperAPI MCP server
Keywords: http,mcp,llm,automation,scraping
Author: ScraperAPI
Requires-Python: >=3.11
Classifier: Development Status :: 1 - Planning
Classifier: Programming Language :: Python :: 3
Classifier: Programming Language :: Python :: 3.11
Classifier: Programming Language :: Python :: 3.12
Classifier: Programming Language :: Python :: 3.13
Classifier: Programming Language :: Python :: 3.10
Requires-Dist: mcp[cli] (>=1.6.0)
Requires-Dist: pydantic (>=2.11.3)
Requires-Dist: pydantic-settings (>=2.9.1)
Requires-Dist: requests (>=2.32.3)
